pyfields/__init__.py
pyfields/_version.py
pyfields/autofields_.py
pyfields/core.py
pyfields/helpers.py
pyfields/init_makers.py
pyfields/init_makers.pyi
pyfields/py.typed
pyfields/typing_utils.py
pyfields/validate_n_convert.py
pyfields/validate_n_convert.pyi
pyfields-1.7.2.dist-info/LICENSE
pyfields-1.7.2.dist-info/METADATA
pyfields-1.7.2.dist-info/WHEEL
pyfields-1.7.2.dist-info/top_level.txt
pyfields-1.7.2.dist-info/RECORD
