Metadata-Version: 2.1
Name: pyfields
Version: 1.7.2
Summary: Define fields in python classes. Easily.
Home-page: https://github.com/smarie/python-pyfields
Download-URL: https://github.com/smarie/python-pyfields/tarball/1.7.2
Author: Sylvain MARIE <sylvain.marie@se.com>
Maintainer: Sylvain MARIE <sylvain.marie@se.com>
License: BSD 3-Clause
Keywords: object class boilerplate oop field attr member descriptor attribute mix-in mixin validation type-check
Classifier: Development Status :: 5 - Production/Stable
Classifier: Intended Audience :: Developers
Classifier: License :: OSI Approved :: BSD License
Classifier: Topic :: Software Development :: Libraries :: Python Modules
Classifier: Programming Language :: Python
Classifier: Programming Language :: Python :: 2
Classifier: Programming Language :: Python :: 2.7
Classifier: Programming Language :: Python :: 3
Classifier: Programming Language :: Python :: 3.5
Classifier: Programming Language :: Python :: 3.6
Classifier: Programming Language :: Python :: 3.7
Classifier: Programming Language :: Python :: 3.8
Classifier: Programming Language :: Python :: 3.9
License-File: LICENSE
Requires-Dist: valid8 (>=5.0)
Requires-Dist: makefun
Requires-Dist: packaging
Requires-Dist: funcsigs ; python_version < "3.3"
Requires-Dist: enum34 ; python_version < "3.4"
